kiarina/lib/openai/__init__.py
kiarina/lib/openai/_settings.py
kiarina/lib/openai/py.typed
kiarina_lib_openai-1.35.0.dist-info/METADATA
kiarina_lib_openai-1.35.0.dist-info/WHEEL
kiarina_lib_openai-1.35.0.dist-info/RECORD
